{
	"info": {
		"_postman_id": "93901e84-636c-4fb3-8a13-ae86b1b2ca52",
		"name": "inmodochouse",
		"schema": "https://schema.getpostman.com/json/collection/v2.1.0/collection.json",
		"_exporter_id": "22531188"
	},
	"item": [
		{
			"name": "Save Property",
			"request": {
				"auth": {
					"type": "bearer",
					"bearer": [
						{
							"key": "token",
							"value": "eyJhbGciOiJIUzUxMiJ9.eyJzdWIiOiJhZG1pbkBhZG1pbi5jb20iLCJpYXQiOjE2Njk4NDUxOTAsImV4cCI6MTY2OTg4MTE5MH0.WmqWEtkDcTYAHfn0wIPwcxzDnRZDNCdHpylhoiobIeMLSCQ1i-4PeA5iIhU2yjzzd5nIqGvH8oKzs2VnQNfUZQ",
							"type": "string"
						}
					]
				},
				"method": "POST",
				"header": [],
				"body": {
					"mode": "raw",
					"raw": "\r\n{\r\n    \"m2\": 10.5,\r\n    \"quantityOfAmbiences\": 2,\r\n    \"price\": 10000,\r\n    \"quantityOfBathrooms\": 1,\r\n    \"garage\": false,\r\n    \"expense\": 1000,\r\n    \"privateNeighborhood\": false,\r\n    \"typeOperation\": \"Sale\",\r\n    \"userId\": 1,\r\n    \"ubication\": \"villa\",\r\n    \"address\": \"miseria 1686\"\r\n}",
					"options": {
						"raw": {
							"language": "json"
						}
					}
				},
				"url": {
					"raw": "http://localhost:8080/api/property/save",
					"protocol": "http",
					"host": [
						"localhost"
					],
					"port": "8080",
					"path": [
						"api",
						"property",
						"save"
					]
				}
			},
			"response": []
		},
		{
			"name": "Login",
			"request": {
				"auth": {
					"type": "bearer",
					"bearer": [
						{
							"key": "token",
							"value": "",
							"type": "string"
						}
					]
				},
				"method": "POST",
				"header": [],
				"body": {
					"mode": "raw",
					"raw": "\r\n{\r\n    \"usernameOrEmail\":\"admin\",\r\n    \"password\":\"12345678\"\r\n}",
					"options": {
						"raw": {
							"language": "json"
						}
					}
				},
				"url": {
					"raw": "http://localhost:8080/api/auth/login",
					"protocol": "http",
					"host": [
						"localhost"
					],
					"port": "8080",
					"path": [
						"api",
						"auth",
						"login"
					]
				}
			},
			"response": []
		},
		{
			"name": "Signin",
			"request": {
				"auth": {
					"type": "bearer",
					"bearer": [
						{
							"key": "token",
							"value": "",
							"type": "string"
						}
					]
				},
				"method": "POST",
				"header": [],
				"body": {
					"mode": "raw",
					"raw": "\r\n{\r\n    \"usernameOrEmail\":\"admin\",\r\n    \"password\":\"12345678\"\r\n}",
					"options": {
						"raw": {
							"language": "json"
						}
					}
				},
				"url": {
					"raw": "http://localhost:8080/api/auth/signin",
					"protocol": "http",
					"host": [
						"localhost"
					],
					"port": "8080",
					"path": [
						"api",
						"auth",
						"signin"
					]
				}
			},
			"response": []
		}
	]
}